LICENSE
README.rst
setup.py
city_planner_project.egg-info/PKG-INFO
city_planner_project.egg-info/SOURCES.txt
city_planner_project.egg-info/dependency_links.txt
city_planner_project.egg-info/top_level.txt
src/__init__.py
src/main.py
src/tools.py
tests/__init__.py
tests/tools_test.py